LICENSE
README.md
setup.py
HaulEnc.egg-info/PKG-INFO
HaulEnc.egg-info/SOURCES.txt
HaulEnc.egg-info/dependency_links.txt
HaulEnc.egg-info/entry_points.txt
HaulEnc.egg-info/requires.txt
HaulEnc.egg-info/top_level.txt
haul/__init__.py
haul/main.py