Metadata-Version: 2.1
Name: HaulEnc
Version: 0.1
Summary: A Python-based file encryption and decryption toolkit.
Home-page: https://github.com/arul637/Encryptor
Author: Arulkumaran S
Author-email: sarulkumaran.21042004@gmail.com
License: UNKNOWN
Platform: UNKNOWN
Classifier: Programming Language :: Python :: 3
Classifier: License :: OSI Approved :: MIT License
Classifier: Operating System :: OS Independent
Requires-Python: >=3.6
License-File: LICENSE
